pyupp.py
setup.py
pyupp.egg-info/PKG-INFO
pyupp.egg-info/SOURCES.txt
pyupp.egg-info/dependency_links.txt
pyupp.egg-info/top_level.txt