Metadata-Version: 1.1
Name: pyupp
Version: 0.2
Summary: Read and write unity player preferences data.
Home-page: https://github.com/fmoo/pyupp
Author: Peter Ruibal
Author-email: ruibalp@gmail.com
License: Apache
Keywords: unity
Platform: UNKNOWN
Classifier: Development Status :: 3 - Alpha
Classifier: Intended Audience :: Developers
Classifier: License :: OSI Approved :: Apache Software License
Classifier: Operating System :: OS Independent
Classifier: Programming Language :: Python :: 2.6
Classifier: Programming Language :: Python :: 2.7
Classifier: Programming Language :: Python :: 2 :: Only
Classifier: Topic :: Software Development :: Libraries
Requires: six
